README.md
setup.py
nonebot_plugin_jrrp2/__init__.py
nonebot_plugin_jrrp2.egg-info/PKG-INFO
nonebot_plugin_jrrp2.egg-info/SOURCES.txt
nonebot_plugin_jrrp2.egg-info/dependency_links.txt
nonebot_plugin_jrrp2.egg-info/requires.txt
nonebot_plugin_jrrp2.egg-info/top_level.txt