Metadata-Version: 1.1
Name: nonebot-plugin-jrrp2
Version: 1.6
Summary: nonebot2带数据库可查询历史平均人品的jrrp插件
Home-page: https://github.com/Rene8028/nonebot_plugin_jrrp2
Author: Rene8028
Author-email: Rene8028@outlook.com
License: MIT License
Platform: all
Classifier: Development Status :: 4 - Beta
Classifier: Operating System :: OS Independent
Classifier: Intended Audience :: Developers
Classifier: License :: OSI Approved :: MIT License
Classifier: Programming Language :: Python
Classifier: Programming Language :: Python :: 2
Classifier: Programming Language :: Python :: 2.7
Classifier: Programming Language :: Python :: 3
Classifier: Programming Language :: Python :: 3.5
Classifier: Programming Language :: Python :: 3.6
Classifier: Programming Language :: Python :: 3.7
Classifier: Programming Language :: Python :: 3.8
Classifier: Programming Language :: Python :: 3.9
